mkdocs_puml_file/__init__.py
mkdocs_puml_file/plugin.py
mkdocs_puml_file-1.0.3.dist-info/LICENSE
mkdocs_puml_file-1.0.3.dist-info/METADATA
mkdocs_puml_file-1.0.3.dist-info/WHEEL
mkdocs_puml_file-1.0.3.dist-info/entry_points.txt
mkdocs_puml_file-1.0.3.dist-info/top_level.txt
mkdocs_puml_file-1.0.3.dist-info/RECORD
