Metadata-Version: 2.2
Name: mkdocs_puml_file
Version: 1.0.3
Summary: A MkDocs plugin that allows to embed PlantUML files.
Home-page: https://github.com/TomMeHo/mkdocs_puml_file
Author: Thomas Meder
License: MIT
Keywords: mkdocs plantuml publishing documentation uml sequence diagram
Classifier: Development Status :: 5 - Production/Stable
Classifier: License :: OSI Approved :: MIT License
Classifier: Operating System :: OS Independent
Classifier: Programming Language :: Python :: 3
License-File: LICENSE
Requires-Dist: mkdocs
Dynamic: author
Dynamic: classifier
Dynamic: description
Dynamic: description-content-type
Dynamic: home-page
Dynamic: keywords
Dynamic: license
Dynamic: requires-dist
Dynamic: summary
